{"code":200,"message":"ok","data":{"total":"64","list":[{"id":"1294","account_type":"1","zfx_symbol":"AUDCAD","symbol_type":"1","mt4_symbol":"AUDCAD","product_name":"Australian Dollar vs Canadian Dollar","spread":"0.00023","overnight_rate_bug":"Refer to terminal data","overnight_rate_sell":"Refer to terminal data","buy_min_margin_rate":"0.25%","trade_time":"Sunday 17:05 - Friday 16:55 (New York time)"},{"id":"1296","account_type":"1","zfx_symbol":"AUDCHF","symbol_type":"1","mt4_symbol":"AUDCHF","product_name":"Australian Dollar vs Swiss Franc","spread":"0.00021","overnight_rate_bug":"Refer to terminal data","overnight_rate_sell":"Refer to terminal data","buy_min_margin_rate":"0.25%","trade_time":"Sunday 17:05 - Friday 16:55 (New York time)"},{"id":"1283","account_type":"1","zfx_symbol":"AUDJPY","symbol_type":"1","mt4_symbol":"AUDJPY","product_name":"Australian Dollar vs Japanese Yen","spread":"0.02","overnight_rate_bug":"Refer to terminal data","overnight_rate_sell":"Refer to terminal data","buy_min_margin_rate":"0.25%","trade_time":"Sunday 17:05 - Friday 16:55 (New York time)"},{"id":"1295","account_type":"1","zfx_symbol":"AUDNZD","symbol_type":"1","mt4_symbol":"AUDNZD","product_name":"Australian Dollar vs New Zealand","spread":"0.00033","overnight_rate_bug":"Refer to terminal data","overnight_rate_sell":"Refer to terminal data","buy_min_margin_rate":"0.25%","trade_time":"Sunday 17:05 - Friday 16:55 (New York time)"},{"id":"1279","account_type":"1","zfx_symbol":"AUDUSD","symbol_type":"1","mt4_symbol":"AUDUSD","product_name":"Australian Dollar vs US Dollar","spread":"0.00015","overnight_rate_bug":"Refer to terminal data","overnight_rate_sell":"Refer to terminal data","buy_min_margin_rate":"0.25%","trade_time":"Sunday 17:05 - Friday 16:55 (New York time)"},{"id":"1297","account_type":"1","zfx_symbol":"CADCHF","symbol_type":"1","mt4_symbol":"CADCHF","product_name":"Canadian Dollar vs Swiss Franc","spread":"0.00023","overnight_rate_bug":"Refer to terminal data","overnight_rate_sell":"Refer to terminal data","buy_min_margin_rate":"0.25%","trade_time":"Sunday 17:05 - Friday 16:55 (New York time)"},{"id":"1284","account_type":"1","zfx_symbol":"CADJPY","symbol_type":"1","mt4_symbol":"CADJPY","product_name":"Canadian Dollar vs Japanese Yen","spread":"0.022","overnight_rate_bug":"Refer to terminal data","overnight_rate_sell":"Refer to terminal data","buy_min_margin_rate":"0.25%","trade_time":"Sunday 17:05 - Friday 16:55 (New York time)"},{"id":"1298","account_type":"1","zfx_symbol":"CHFJPY","symbol_type":"1","mt4_symbol":"CHFJPY","product_name":"Swiss Franc vs Japanise Yen","spread":"0.024","overnight_rate_bug":"Refer to terminal data","overnight_rate_sell":"Refer to terminal data","buy_min_margin_rate":"0.25%","trade_time":"Sunday 17:05 - Friday 16:55 (New York time)"},{"id":"1286","account_type":"1","zfx_symbol":"EURAUD","symbol_type":"1","mt4_symbol":"EURAUD","product_name":"Euro vs Australian Dollar","spread":"0.00025","overnight_rate_bug":"Refer to terminal data","overnight_rate_sell":"Refer to terminal data","buy_min_margin_rate":"0.25%","trade_time":"Sunday 17:05 - Friday 16:55 (New York time)"},{"id":"1289","account_type":"1","zfx_symbol":"EURCAD","symbol_type":"1","mt4_symbol":"EURCAD","product_name":"Euro vs Canadian Dollar","spread":"0.00025","overnight_rate_bug":"Refer to terminal data","overnight_rate_sell":"Refer to terminal data","buy_min_margin_rate":"0.25%","trade_time":"Sunday 17:05 - Friday 16:55 (New York time)"},{"id":"1299","account_type":"1","zfx_symbol":"EURCHF","symbol_type":"1","mt4_symbol":"EURCHF","product_name":"Euro vs Swiss Franc","spread":"0.00022","overnight_rate_bug":"Refer to terminal data","overnight_rate_sell":"Refer to terminal data","buy_min_margin_rate":"0.25%","trade_time":"Sunday 17:05 - Friday 16:55 (New York time)"},{"id":"889","account_type":"1","zfx_symbol":"EURDKK","symbol_type":"1","mt4_symbol":"EURDKK","product_name":"Euro vs Danish Krone","spread":"0.00192","overnight_rate_bug":"Refer to terminal data","overnight_rate_sell":"Refer to terminal data","buy_min_margin_rate":"0.25%","trade_time":"Sunday 17:05 - Friday 16:55 (New York time)"},{"id":"1285","account_type":"1","zfx_symbol":"EURGBP","symbol_type":"1","mt4_symbol":"EURGBP","product_name":"Euro vs British Pound","spread":"0.00021","overnight_rate_bug":"Refer to terminal data","overnight_rate_sell":"Refer to terminal data","buy_min_margin_rate":"0.25%","trade_time":"Sunday 17:05 - Friday 16:55 (New York time)"},{"id":"890","account_type":"1","zfx_symbol":"EURHKD","symbol_type":"1","mt4_symbol":"EURHKD","product_name":"Euro vs Hong Kong Dollar","spread":"0.00173","overnight_rate_bug":"Refer to terminal data","overnight_rate_sell":"Refer to terminal data","buy_min_margin_rate":"0.25%","trade_time":"Sunday 17:05 - Friday 16:55 (New York time)"},{"id":"1281","account_type":"1","zfx_symbol":"EURJPY","symbol_type":"1","mt4_symbol":"EURJPY","product_name":"Euro vs Japanese Yen","spread":"0.02","overnight_rate_bug":"Refer to terminal data","overnight_rate_sell":"Refer to terminal data","buy_min_margin_rate":"0.25%","trade_time":"Sunday 17:05 - Friday 16:55 (New York time)"},{"id":"891","account_type":"1","zfx_symbol":"EURMXN","symbol_type":"1","mt4_symbol":"EURMXN","product_name":"Euro vs Mexican Peso","spread":"0.0099","overnight_rate_bug":"Refer to terminal data","overnight_rate_sell":"Refer to terminal data","buy_min_margin_rate":"0.25%","trade_time":"Sunday 17:05 - Friday 16:55 (New York time)"},{"id":"892","account_type":"1","zfx_symbol":"EURNOK","symbol_type":"1","mt4_symbol":"EURNOK","product_name":"Euro vs Norwegian Krone","spread":"0.00393","overnight_rate_bug":"Refer to terminal data","overnight_rate_sell":"Refer to terminal data","buy_min_margin_rate":"0.25%","trade_time":"Sunday 17:05 - Friday 16:55 (New York time)"},{"id":"1300","account_type":"1","zfx_symbol":"EURNZD","symbol_type":"1","mt4_symbol":"EURNZD","product_name":"Euro vs New Zealand Dollar","spread":"0.00024","overnight_rate_bug":"Refer to terminal data","overnight_rate_sell":"Refer to terminal data","buy_min_margin_rate":"0.25%","trade_time":"Sunday 17:05 - Friday 16:55 (New York time)"},{"id":"893","account_type":"1","zfx_symbol":"EURPLN","symbol_type":"1","mt4_symbol":"EURPLN","product_name":"Euro vs Polish Zloty","spread":"0.00204","overnight_rate_bug":"Refer to terminal data","overnight_rate_sell":"Refer to terminal data","buy_min_margin_rate":"0.25%","trade_time":"Sunday 17:05 - Friday 16:55 (New York time)"},{"id":"894","account_type":"1","zfx_symbol":"EURRUB","symbol_type":"1","mt4_symbol":"EURRUB","product_name":"Euro vs Russian Ruble","spread":"0.09145","overnight_rate_bug":"Refer to terminal data","overnight_rate_sell":"Refer to terminal data","buy_min_margin_rate":"0.25%","trade_time":"Sunday 17:05 - Friday 16:55 (New York time)"},{"id":"895","account_type":"1","zfx_symbol":"EURSEK","symbol_type":"1","mt4_symbol":"EURSEK","product_name":"Euro vs Swedish Krona","spread":"0.00363","overnight_rate_bug":"Refer to terminal data","overnight_rate_sell":"Refer to terminal data","buy_min_margin_rate":"0.25%","trade_time":"Sunday 17:05 - Friday 16:55 (New York time)"},{"id":"896","account_type":"1","zfx_symbol":"EURSGD","symbol_type":"1","mt4_symbol":"EURSGD","product_name":"Euro vs Singapore Dollar","spread":"0.0004","overnight_rate_bug":"Refer to terminal data","overnight_rate_sell":"Refer to terminal data","buy_min_margin_rate":"0.25%","trade_time":"Sunday 17:05 - Friday 16:55 (New York time)"},{"id":"1292","account_type":"1","zfx_symbol":"EURTRY","symbol_type":"1","mt4_symbol":"EURTRY","product_name":"Euro vs Turkish Lira","spread":"0.00869","overnight_rate_bug":"Refer to terminal data","overnight_rate_sell":"Refer to terminal data","buy_min_margin_rate":"0.25%","trade_time":"Sunday 17:05 - Friday 16:55 (New York time)"},{"id":"1274","account_type":"1","zfx_symbol":"EURUSD","symbol_type":"1","mt4_symbol":"EURUSD","product_name":"Euro vs US Dollar","spread":"0.00013","overnight_rate_bug":"Refer to terminal data","overnight_rate_sell":"Refer to terminal data","buy_min_margin_rate":"0.25%","trade_time":"Sunday 17:05 - Friday 16:55 (New York time)"},{"id":"897","account_type":"1","zfx_symbol":"EURZAR","symbol_type":"1","mt4_symbol":"EURZAR","product_name":"Euro vs South African Rand","spread":"0.00929","overnight_rate_bug":"Refer to terminal data","overnight_rate_sell":"Refer to terminal data","buy_min_margin_rate":"0.25%","trade_time":"Sunday 17:05 - Friday 16:55 (New York time)"},{"id":"1287","account_type":"1","zfx_symbol":"GBPAUD","symbol_type":"1","mt4_symbol":"GBPAUD","product_name":"British Pound vs Australian Dollar","spread":"0.00042","overnight_rate_bug":"Refer to terminal data","overnight_rate_sell":"Refer to terminal data","buy_min_margin_rate":"0.25%","trade_time":"Sunday 17:05 - Friday 16:55 (New York time)"},{"id":"1290","account_type":"1","zfx_symbol":"GBPCAD","symbol_type":"1","mt4_symbol":"GBPCAD","product_name":"British Pound vs Canadian Dollar","spread":"0.00036","overnight_rate_bug":"Refer to terminal data","overnight_rate_sell":"Refer to terminal data","buy_min_margin_rate":"0.25%","trade_time":"Sunday 17:05 - Friday 16:55 (New York time)"},{"id":"1302","account_type":"1","zfx_symbol":"GBPCHF","symbol_type":"1","mt4_symbol":"GBPCHF","product_name":"British Pound vs Swiss Franc","spread":"0.00025","overnight_rate_bug":"Refer to terminal data","overnight_rate_sell":"Refer to terminal data","buy_min_margin_rate":"0.25%","trade_time":"Sunday 17:05 - Friday 16:55 (New York time)"},{"id":"898","account_type":"1","zfx_symbol":"GBPDKK","symbol_type":"1","mt4_symbol":"GBPDKK","product_name":"British Pound vs Danish Krone","spread":"0.00346","overnight_rate_bug":"Refer to terminal data","overnight_rate_sell":"Refer to terminal data","buy_min_margin_rate":"0.25%","trade_time":"Sunday 17:05 - Friday 16:55 (New York time)"},{"id":"1282","account_type":"1","zfx_symbol":"GBPJPY","symbol_type":"1","mt4_symbol":"GBPJPY","product_name":"British Pound vs Japanese Yen","spread":"0.024","overnight_rate_bug":"Refer to terminal data","overnight_rate_sell":"Refer to terminal data","buy_min_margin_rate":"0.25%","trade_time":"Sunday 17:05 - Friday 16:55 (New York time)"},{"id":"899","account_type":"1","zfx_symbol":"GBPMXN","symbol_type":"1","mt4_symbol":"GBPMXN","product_name":"British Pound vs Mexican Peso","spread":"0.01398","overnight_rate_bug":"Refer to terminal data","overnight_rate_sell":"Refer to terminal data","buy_min_margin_rate":"0.25%","trade_time":"Sunday 17:05 - Friday 16:55 (New York time)"},{"id":"900","account_type":"1","zfx_symbol":"GBPNOK","symbol_type":"1","mt4_symbol":"GBPNOK","product_name":"British Pound vs Norwegian Krone","spread":"0.00573","overnight_rate_bug":"Refer to terminal data","overnight_rate_sell":"Refer to terminal data","buy_min_margin_rate":"0.25%","trade_time":"Sunday 17:05 - Friday 16:55 (New York time)"},{"id":"1301","account_type":"1","zfx_symbol":"GBPNZD","symbol_type":"1","mt4_symbol":"GBPNZD","product_name":"British Pound vs New Zealand Dollar","spread":"0.00058","overnight_rate_bug":"Refer to terminal data","overnight_rate_sell":"Refer to terminal data","buy_min_margin_rate":"0.25%","trade_time":"Sunday 17:05 - Friday 16:55 (New York time)"},{"id":"901","account_type":"1","zfx_symbol":"GBPPLN","symbol_type":"1","mt4_symbol":"GBPPLN","product_name":"British Pound vs Polish Zloty","spread":"0.00287","overnight_rate_bug":"Refer to terminal data","overnight_rate_sell":"Refer to terminal data","buy_min_margin_rate":"0.25%","trade_time":"Sunday 17:05 - Friday 16:55 (New York time)"},{"id":"902","account_type":"1","zfx_symbol":"GBPSEK","symbol_type":"1","mt4_symbol":"GBPSEK","product_name":"British Pound vs Swedish Krona","spread":"0.00521","overnight_rate_bug":"Refer to terminal data","overnight_rate_sell":"Refer to terminal data","buy_min_margin_rate":"0.25%","trade_time":"Sunday 17:05 - Friday 16:55 (New York time)"},{"id":"903","account_type":"1","zfx_symbol":"GBPSGD","symbol_type":"1","mt4_symbol":"GBPSGD","product_name":"British Pound vs Singapore Dollar","spread":"0.00058","overnight_rate_bug":"Refer to terminal data","overnight_rate_sell":"Refer to terminal data","buy_min_margin_rate":"0.25%","trade_time":"Sunday 17:05 - Friday 16:55 (New York time)"},{"id":"904","account_type":"1","zfx_symbol":"GBPTRY","symbol_type":"1","mt4_symbol":"GBPTRY","product_name":"British Pound vs Turkish Lira","spread":"0.00947","overnight_rate_bug":"Refer to terminal data","overnight_rate_sell":"Refer to terminal data","buy_min_margin_rate":"0.25%","trade_time":"Sunday 17:05 - Friday 16:55 (New York time)"},{"id":"1276","account_type":"1","zfx_symbol":"GBPUSD","symbol_type":"1","mt4_symbol":"GBPUSD","product_name":"British Pound vs US Dollar","spread":"0.00015","overnight_rate_bug":"Refer to terminal data","overnight_rate_sell":"Refer to terminal data","buy_min_margin_rate":"0.25%","trade_time":"Sunday 17:05 - Friday 16:55 (New York time)"},{"id":"905","account_type":"1","zfx_symbol":"GBPZAR","symbol_type":"1","mt4_symbol":"GBPZAR","product_name":"British Pound vs South African Rand","spread":"0.01047","overnight_rate_bug":"Refer to terminal data","overnight_rate_sell":"Refer to terminal data","buy_min_margin_rate":"0.25%","trade_time":"Sunday 17:05 - Friday 16:55 (New York time)"},{"id":"1288","account_type":"1","zfx_symbol":"NZDCAD","symbol_type":"1","mt4_symbol":"NZDCAD","product_name":"New Zealand Dollar vs Canadian Dollar","spread":"0.00027","overnight_rate_bug":"Refer to terminal data","overnight_rate_sell":"Refer to terminal data","buy_min_margin_rate":"0.25%","trade_time":"Sunday 17:05 - Friday 16:55 (New York time)"},{"id":"1303","account_type":"1","zfx_symbol":"NZDCHF","symbol_type":"1","mt4_symbol":"NZDCHF","product_name":"New Zealand Dollar vs Swiss Franc","spread":"0.00035","overnight_rate_bug":"Refer to terminal data","overnight_rate_sell":"Refer to terminal data","buy_min_margin_rate":"0.25%","trade_time":"Sunday 17:05 - Friday 16:55 (New York time)"},{"id":"1306","account_type":"1","zfx_symbol":"NZDJPY","symbol_type":"1","mt4_symbol":"NZDJPY","product_name":"New Zealand Dollar vs Japanese Yen","spread":"0.023","overnight_rate_bug":"Refer to terminal data","overnight_rate_sell":"Refer to terminal data","buy_min_margin_rate":"0.25%","trade_time":"Sunday 17:05 - Friday 16:55 (New York time)"},{"id":"1280","account_type":"1","zfx_symbol":"NZDUSD","symbol_type":"1","mt4_symbol":"NZDUSD","product_name":"New Zealand Dollar vs US Dollar","spread":"0.0002","overnight_rate_bug":"Refer to terminal data","overnight_rate_sell":"Refer to terminal data","buy_min_margin_rate":"0.25%","trade_time":"Sunday 17:05 - Friday 16:55 (New York time)"},{"id":"906","account_type":"1","zfx_symbol":"USDBRL","symbol_type":"1","mt4_symbol":"USDBRL","product_name":"US Dollar vs Brazilian Real","spread":"0.00646","overnight_rate_bug":"Refer to terminal data","overnight_rate_sell":"Refer to terminal data","buy_min_margin_rate":"0.25%","trade_time":"Sunday 17:05 - Friday 16:55, Temporarily Close 21:00-13:11 (New York time)"},{"id":"1278","account_type":"1","zfx_symbol":"USDCAD","symbol_type":"1","mt4_symbol":"USDCAD","product_name":"US Dollar vs Canadian Dollar","spread":"0.00016","overnight_rate_bug":"Refer to terminal data","overnight_rate_sell":"Refer to terminal data","buy_min_margin_rate":"0.25%","trade_time":"Sunday 17:05 - Friday 16:55 (New York time)"},{"id":"1277","account_type":"1","zfx_symbol":"USDCHF","symbol_type":"1","mt4_symbol":"USDCHF","product_name":"US Dollar vs Swiss Franc","spread":"0.00016","overnight_rate_bug":"Refer to terminal data","overnight_rate_sell":"Refer to terminal data","buy_min_margin_rate":"0.25%","trade_time":"Sunday 17:05 - Friday 16:55 (New York time)"},{"id":"1291","account_type":"1","zfx_symbol":"USDCNH","symbol_type":"1","mt4_symbol":"USDCNH","product_name":"US Dollar vs Chinese Yuan (offshore)","spread":"0.00119","overnight_rate_bug":"Refer to terminal data","overnight_rate_sell":"Refer to terminal data","buy_min_margin_rate":"0.25%","trade_time":"Sunday 17:05 - Friday 16:55 (New York time)"},{"id":"907","account_type":"1","zfx_symbol":"USDCZK","symbol_type":"1","mt4_symbol":"USDCZK","product_name":"US Dollar vs Czech Koruna","spread":"0.0261","overnight_rate_bug":"Refer to terminal data","overnight_rate_sell":"Refer to terminal data","buy_min_margin_rate":"0.25%","trade_time":"Sunday 17:05 - Friday 16:55 (New York time)"},{"id":"908","account_type":"1","zfx_symbol":"USDDKK","symbol_type":"1","mt4_symbol":"USDDKK","product_name":"US Dollar vs Danish Krone","spread":"0.00147","overnight_rate_bug":"Refer to terminal data","overnight_rate_sell":"Refer to terminal data","buy_min_margin_rate":"0.25%","trade_time":"Sunday 17:05 - Friday 16:55 (New York time)"},{"id":"1307","account_type":"1","zfx_symbol":"USDHKD","symbol_type":"1","mt4_symbol":"USDHKD","product_name":"US Dollar vs Hong Kong Dollar","spread":"0.00126","overnight_rate_bug":"Refer to terminal data","overnight_rate_sell":"Refer to terminal data","buy_min_margin_rate":"0.25%","trade_time":"Sunday 17:05 - Friday 16:55 (New York time)"},{"id":"909","account_type":"1","zfx_symbol":"USDHUF","symbol_type":"1","mt4_symbol":"USDHUF","product_name":"US Dollar vs Hungarian Forint","spread":"0.346","overnight_rate_bug":"Refer to terminal data","overnight_rate_sell":"Refer to terminal data","buy_min_margin_rate":"0.25%","trade_time":"Sunday 17:05 - Friday 16:55 (New York time)"},{"id":"1308","account_type":"1","zfx_symbol":"USDINR","symbol_type":"1","mt4_symbol":"USDINR","product_name":"US Dollar vs Indian Rupee","spread":"0.10086","overnight_rate_bug":"Refer to terminal data","overnight_rate_sell":"Refer to terminal data","buy_min_margin_rate":"0.25%","trade_time":"Sunday 17:05 - Friday 16:55, Temporarily Close 21:00-03:31 (New York time)"},{"id":"1275","account_type":"1","zfx_symbol":"USDJPY","symbol_type":"1","mt4_symbol":"USDJPY","product_name":"US Dollar vs Japanese Yen","spread":"0.014","overnight_rate_bug":"Refer to terminal data","overnight_rate_sell":"Refer to terminal data","buy_min_margin_rate":"0.25%","trade_time":"Sunday 17:05 - Friday 16:55 (New York time)"},{"id":"910","account_type":"1","zfx_symbol":"USDKRW","symbol_type":"1","mt4_symbol":"USDKRW","product_name":"US Dollar vs South Korean Won","spread":"0.35481","overnight_rate_bug":"Refer to terminal data","overnight_rate_sell":"Refer to terminal data","buy_min_margin_rate":"0.25%","trade_time":"Sunday 17:05 - Friday 16:55, Temporarily Close at 21:00-02:01 (New York time)"},{"id":"911","account_type":"1","zfx_symbol":"USDMXN","symbol_type":"1","mt4_symbol":"USDMXN","product_name":"US Dollar vs Mexican Peso","spread":"0.00756","overnight_rate_bug":"Refer to terminal data","overnight_rate_sell":"Refer to terminal data","buy_min_margin_rate":"0.25%","trade_time":"Sunday 17:05 - Friday 16:55 (New York time)"},{"id":"1305","account_type":"1","zfx_symbol":"USDNOK","symbol_type":"1","mt4_symbol":"USDNOK","product_name":"US Dollar vs Norwegian Krone","spread":"0.00431","overnight_rate_bug":"Refer to terminal data","overnight_rate_sell":"Refer to terminal data","buy_min_margin_rate":"0.25%","trade_time":"Sunday 17:05 - Friday 16:55 (New York time)"},{"id":"912","account_type":"1","zfx_symbol":"USDPLN","symbol_type":"1","mt4_symbol":"USDPLN","product_name":"US Dollar vs Polish Zloty","spread":"0.00185","overnight_rate_bug":"Refer to terminal data","overnight_rate_sell":"Refer to terminal data","buy_min_margin_rate":"0.25%","trade_time":"Sunday 17:05 - Friday 16:55 (New York time)"},{"id":"913","account_type":"1","zfx_symbol":"USDRUB","symbol_type":"1","mt4_symbol":"USDRUB","product_name":"US Dollar vs Russian Ruble","spread":"0.03174","overnight_rate_bug":"Refer to terminal data","overnight_rate_sell":"Refer to terminal data","buy_min_margin_rate":"0.25%","trade_time":"Sunday 17:05 - Friday 16:55 (New York time)"},{"id":"914","account_type":"1","zfx_symbol":"USDSEK","symbol_type":"1","mt4_symbol":"USDSEK","product_name":"US Dollar vs Swedish Krona","spread":"0.00296","overnight_rate_bug":"Refer to terminal data","overnight_rate_sell":"Refer to terminal data","buy_min_margin_rate":"0.25%","trade_time":"Sunday 17:05 - Friday 16:55 (New York time)"},{"id":"1304","account_type":"1","zfx_symbol":"USDSGD","symbol_type":"1","mt4_symbol":"USDSGD","product_name":"US Dollar vs Singapore Dollar","spread":"0.00044","overnight_rate_bug":"Refer to terminal data","overnight_rate_sell":"Refer to terminal data","buy_min_margin_rate":"0.25%","trade_time":"Sunday 17:05 - Friday 16:55 (New York time)"},{"id":"915","account_type":"1","zfx_symbol":"USDTHB","symbol_type":"1","mt4_symbol":"USDTHB","product_name":"US Dollar vs Thai Baht","spread":"0.039","overnight_rate_bug":"Refer to terminal data","overnight_rate_sell":"Refer to terminal data","buy_min_margin_rate":"0.25%","trade_time":"Sunday 17:05 - Friday 16:55 (New York time)"},{"id":"1293","account_type":"1","zfx_symbol":"USDTRY","symbol_type":"1","mt4_symbol":"USDTRY","product_name":"US Dollar vs Turkish Lira","spread":"0.00547","overnight_rate_bug":"Refer to terminal data","overnight_rate_sell":"Refer to terminal data","buy_min_margin_rate":"0.25%","trade_time":"Sunday 17:05 - Friday 16:55 (New York time)"},{"id":"916","account_type":"1","zfx_symbol":"USDTWD","symbol_type":"1","mt4_symbol":"USDTWD","product_name":"US Dollar vs Taiwan Dollar","spread":"0.01756","overnight_rate_bug":"Refer to terminal data","overnight_rate_sell":"Refer to terminal data","buy_min_margin_rate":"0.25%","trade_time":"Sunday 17:05 - Friday 16:55 (New York time)"},{"id":"917","account_type":"1","zfx_symbol":"USDZAR","symbol_type":"1","mt4_symbol":"USDZAR","product_name":"US Dollar vs South African Rand","spread":"0.00728","overnight_rate_bug":"Refer to terminal data","overnight_rate_sell":"Refer to terminal data","buy_min_margin_rate":"2.00%","trade_time":"Sunday 17:05 - Friday 16:55 (New York time)"}]},"timestamp":1664518552}